{"dst_rtts": [29.789, 28.54, 29.268], "dst_prb_id": 25337, "protocol": 6, "msm_id": 3742566, "as_links": {"nodes": ["AS6939", "_DIX", "AS3308", "AS65101", "AS1299"], "links": [{"src": "AS1299", "dst": "AS3308", "type": "d"}, {"src": "_DIX", "dst": "AS6939", "type": "d"}, {"src": "AS6939", "dst": "AS1299", "type": "d"}, {"src": "AS65101", "dst": "_DIX", "type": "d"}]}, "locations": ["Stockholm,Stockholm,SE", "Hamburg,Hamburg,DE", "Amsterdam,North Holland,NL", "Copenhagen,Capital Region,DK"], "geojson": [{"type": "LineString", "coordinates": [["12.5805", "55.6115"], ["12.56553", "55.67594"]]}, {"type": "LineString", "coordinates": [["12.56553", "55.67594"], ["10.01534", "53.57532"]]}, {"type": "LineString", "coordinates": [["10.01534", "53.57532"], ["4.88969", "52.37403"]]}, {"type": "LineString", "coordinates": [["4.88969", "52.37403"], ["18.0649", "59.33258"]]}, {"type": "LineString", "coordinates": [[18.0649, 59.33258], [11.5585, 55.4405]]}], "ts": 1462172972, "tracetxt": "## msm_id:3742566 prb_id:3468 dst:2001:2012:3ec6:9cec:c66e:1fff:fe5b:caa6 ts:2016-05-02 07:09:32 -00:00\n1 (AS65101) 2a02:2190:f000:cf0f::1 [5.37, 5.576, 201.292] ||\n2 (AS65101) 2a02:2190:1004:da::1 [6.362, 6.534, 6.723] ||\n3 (AS65101) 2a02:2190:1:1::1 [4.71, 5.865, 5.878] ||\n4 (AS1835) 2001:7f8:1f::6939:38:0 [5.821, 9.231, 13.663] |Copenhagen,Capital Region,DK|\n5 (AS6939) 10ge16-1.core1.ham1.he.net [11.807, 12.406, 26.817] |Hamburg,Hamburg,DE|\n6 (AS6939) 10ge11-6.core1.ams1.he.net [17.655, 39.322, 49.957] |Amsterdam,North Holland,NL|\n7 (AS1299) adm-sara-s1-link.telia.net [18.275, 18.44, 18.622] |Amsterdam,North Holland,NL|\n8 (AS1299) kbn-b4-v6.telia.net [18.667, 18.804, 19.051] |Stockholm,Stockholm,SE|\n9 (AS1299) haproxy-ic-312321-las-b21.c.telia.net [19.663, 19.683, 21.11] ||\n10 (AS3308) 2001:2000:1080:16::1 [19.12, 19.163, 19.258] ||\n11 (AS3308) 2001:2000:1080:16::2 [19.746, 19.988, 20.099] ||\n12 err:{u'x': u'*'}\n13 (AS3308) 2001:2012:3ec6:9cec:c66e:1fff:fe5b:caa6 [28.54, 29.268, 29.789] ||\n", "result": [{"result": [{"rtt": 201.292, "size": 96, "from": "2a02:2190:f000:cf0f::1", "ttl": 64}, {"rtt": 5.576, "size": 96, "from": "2a02:2190:f000:cf0f::1", "ttl": 64}, {"rtt": 5.37, "size": 96, "from": "2a02:2190:f000:cf0f::1", "ttl": 64}], "hop": 1}, {"result": [{"rtt": 6.723, "size": 96, "from": "2a02:2190:1004:da::1", "ttl": 63}, {"rtt": 6.362, "size": 96, "from": "2a02:2190:1004:da::1", "ttl": 63}, {"rtt": 6.534, "size": 96, "from": "2a02:2190:1004:da::1", "ttl": 63}], "hop": 2}, {"result": [{"rtt": 5.865, "size": 96, "from": "2a02:2190:1:1::1", "ttl": 62}, {"rtt": 5.878, "size": 96, "from": "2a02:2190:1:1::1", "ttl": 62}, {"rtt": 4.71, "size": 96, "from": "2a02:2190:1:1::1", "ttl": 62}], "hop": 3}, {"result": [{"rtt": 13.663, "size": 96, "from": "2001:7f8:1f::6939:38:0", "ttl": 57}, {"rtt": 9.231, "size": 96, "from": "2001:7f8:1f::6939:38:0", "ttl": 57}, {"rtt": 5.821, "size": 96, "from": "2001:7f8:1f::6939:38:0", "ttl": 57}], "hop": 4}, {"result": [{"rtt": 26.817, "size": 96, "from": "2001:470:0:30e::2", "ttl": 56}, {"rtt": 12.406, "size": 96, "from": "2001:470:0:30e::2", "ttl": 56}, {"rtt": 11.807, "size": 96, "from": "2001:470:0:30e::2", "ttl": 56}], "hop": 5}, {"result": [{"rtt": 49.957, "size": 96, "from": "2001:470:0:30d::1", "ttl": 57}, {"rtt": 17.655, "size": 96, "from": "2001:470:0:30d::1", "ttl": 57}, {"rtt": 39.322, "size": 96, "from": "2001:470:0:30d::1", "ttl": 57}], "hop": 6}, {"result": [{"rtt": 18.275, "size": 96, "from": "2001:2000:3080:1b9::1", "ttl": 56}, {"rtt": 18.44, "size": 96, "from": "2001:2000:3080:1b9::1", "ttl": 56}, {"rtt": 18.622, "size": 96, "from": "2001:2000:3080:1b9::1", "ttl": 56}], "hop": 7}, {"result": [{"rtt": 18.667, "size": 96, "from": "2001:2000:3018:12::1", "ttl": 56}, {"rtt": 19.051, "size": 96, "from": "2001:2000:3018:12::1", "ttl": 56}, {"rtt": 18.804, "size": 96, "from": "2001:2000:3018:12::1", "ttl": 56}], "hop": 8}, {"result": [{"rtt": 19.683, "size": 96, "from": "2001:2000:3080:94::2", "ttl": 55}, {"rtt": 19.663, "size": 96, "from": "2001:2000:3080:94::2", "ttl": 55}, {"rtt": 21.11, "size": 96, "from": "2001:2000:3080:94::2", "ttl": 55}], "hop": 9}, {"result": [{"rtt": 19.163, "size": 96, "from": "2001:2000:1080:16::1", "ttl": 56}, {"rtt": 19.258, "size": 96, "from": "2001:2000:1080:16::1", "ttl": 56}, {"rtt": 19.12, "size": 96, "from": "2001:2000:1080:16::1", "ttl": 56}], "hop": 10}, {"result": [{"rtt": 20.099, "size": 96, "from": "2001:2000:1080:16::2", "ttl": 55}, {"rtt": 19.746, "size": 96, "from": "2001:2000:1080:16::2", "ttl": 55}, {"rtt": 19.988, "size": 96, "from": "2001:2000:1080:16::2", "ttl": 55}], "hop": 11}, {"result": [{"x": "*"}, {"x": "*"}, {"x": "*"}], "hop": 12}, {"result": [{"rtt": 29.789, "size": 48, "from": "2001:2012:3ec6:9cec:c66e:1fff:fe5b:caa6", "ttl": 53}, {"rtt": 28.54, "size": 48, "from": "2001:2012:3ec6:9cec:c66e:1fff:fe5b:caa6", "ttl": 53}, {"rtt": 29.268, "size": 48, "from": "2001:2012:3ec6:9cec:c66e:1fff:fe5b:caa6", "ttl": 53}], "hop": 13}], "src_prb_id": 3468, "in_country": false, "via_ixp": true, "ixps": ["DIX"]}