{"dst_rtts": [8.849, 8.827, 8.951], "dst_prb_id": 11266, "protocol": 4, "msm_id": 3742514, "as_links": {"nodes": [], "links": []}, "locations": [], "geojson": [{"type": "LineString", "coordinates": [[12.5415, 55.6515], [10.1005, 56.2305]]}], "ts": 1462172863, "tracetxt": "## msm_id:3742514 prb_id:19298 dst:87.104.212.66 ts:2016-05-02 07:07:43 -00:00\n1 () 192.168.110.1 [0.507, 0.572, 0.706] ||\n2 * * *\n3 * * *\n4 * * *\n5 * * *\n6 * * *\n6 * * *\n", "result": [{"result": [{"rtt": 0.706, "size": 64, "from": "192.168.110.1", "ttl": 64}, {"rtt": 0.572, "size": 64, "from": "192.168.110.1", "ttl": 64}, {"rtt": 0.507, "size": 64, "from": "192.168.110.1", "ttl": 64}], "hop": 1}, {"result": [{"x": "*"}, {"x": "*"}, {"x": "*"}], "hop": 2}, {"result": [{"x": "*"}, {"x": "*"}, {"x": "*"}], "hop": 3}, {"result": [{"x": "*"}, {"x": "*"}, {"x": "*"}], "hop": 4}, {"result": [{"x": "*"}, {"x": "*"}, {"x": "*"}], "hop": 5}, {"result": [{"x": "*"}, {"x": "*"}, {"x": "*"}], "hop": 6}, {"result": [{"rtt": 8.849, "size": 48, "from": "87.104.212.66", "ttl": 58}, {"rtt": 8.827, "size": 48, "from": "87.104.212.66", "ttl": 58}, {"rtt": 8.951, "size": 48, "from": "87.104.212.66", "ttl": 58}], "hop": 255}], "src_prb_id": 19298, "in_country": true, "via_ixp": false, "ixps": []}